{
  "markov": {
    "correct": 6,
    "total": 8
  },
  "trend": {
    "correct": 5,
    "total": 8
  },
  "anomaly": {
    "correct": 3,
    "total": 8
  },
  "timeseries": {
    "correct": 3,
    "total": 7
  },
  "gametheory": {
    "correct": 4,
    "total": 7
  },
  "adaptive": {
    "correct": 5,
    "total": 8
  },
  "recent": {
    "correct": 4,
    "total": 8
  },
  "quickadaptive": {
    "correct": 5,
    "total": 8
  },
  "learning": {
    "correct": 4,
    "total": 8
  },
  "numberpred": {
    "correct": 5,
    "total": 5
  },
  "recent_trend": {
    "correct": 4,
    "total": 8
  },
  "ensemble": {
    "correct": 3,
    "total": 4
  },
  "pattern": {
    "correct": 1,
    "total": 1
  }
}